{
  "name": "JobProfiles0_50691de8-6801-4c5d-831a-38d843f529f8",
  "displayName": "JobProfiles0_50691de8-6801-4c5d-831a-38d843f529f8",
  "description": "",
  "author": "",
  "website": "",
  "version": "",
  "issetuprecipe": false,
  "categories": "",
  "tags": [],
  "steps": [
    {
      "name": "CSharpContent",
      "data": [
  {
    "TitlePart": {
      "Title": "Actor"
    },
    "JobProfile": {},
    "JobProfileHeader": {
      "Occupation": {
        "ContentItemIds": [
          "\u00ABc#: await Content.GetContentItemIdByDisplayText(\u0022Occupation\u0022, \u0022actor/actress\u0022)\u00BB"
        ]
      },
      "Description": {
        "Html": "\u003Cp\u003EActors use speech, movement and expression to bring characters to life in theatre, film, television and radio.\u003C/p\u003E"
      },
      "TitleOptions": {
        "Text": "as_defined"
      },
      "JobProfileWebsiteUrl": {
        "Text": "actor"
      },
      "SOCCode": {
        "ContentItemIds": [
          "45fqmrg9s3kkstp2kgb3setsw3"
        ]
      },
      "ONetOccupationalCode": {
        "ContentItemIds": [
          "49r0wdzdnc2dh40kyzwjj0vec6"
        ]
      },
      "SalaryStarter": {
        "Text": "variable"
      },
      "SalaryExperienced": {
        "Text": "variable"
      },
      "MinimumHours": {
        "Value": 45.0
      },
      "MaximumHours": {
        "Value": 47.0
      },
      "WorkingHoursDetails": {
        "Text": "irregular"
      },
      "WorkingPattern": {
        "Text": "evenings / weekends / bank holidays"
      },
      "WorkingPatternDetails": {
        "Text": "away from home"
      }
    },
    "HowToBecome": {
      "HowToBecome": null,
      "ApprenticeshipRoute": {
        "ContentItemIds": []
      },
      "CollegeRoute": {
        "ContentItemIds": [
          "4ynehfxjx4ms2v7xc0vyfa8ec9"
        ]
      },
      "UniversityRoute": {
        "ContentItemIds": [
          "4b1r01xg5ahnn3dmxbn8h6rqwx"
        ]
      },
      "DirectRoute": {
        "ContentItemIds": [
          "4ffgbh6txha64tvfez41ckebm5"
        ]
      },
      "OtherRoute": {
        "ContentItemIds": [
          "4yd3cr2esa8rvxb6s9r0mkbknv"
        ]
      },
      "VolunteeringRoute": {
        "ContentItemIds": [
          "4mqjv5sf89jdrsdbmxnhfd2sxk"
        ]
      },
      "WorkRoute": {
        "ContentItemIds": []
      },
      "HtbBodies": {
        "Html": "\u003Cp\u003EYou can join \u003Ca href=\u0022https://www.equity.org.uk/getting-involved/\u0022\u003EEquity\u003C/a\u003E for professional recognition, training opportunities and to make industry contacts.\u003C/p\u003E"
      },
      "HtbCareerTips": {
        "Html": "\u003Cp\u003EYou\u0027ll need to get as much practical experience of acting as you can, and create a showreel to demonstrate your acting skills to agents and casting directors.\u003C/p\u003E"
      },
      "HtbFurtherInformation": {
        "Html": "\u003Cp\u003EYou can find out more about becoming an actor through \u003Ca href=\u0022https://ccskills.org.uk/careers/advice/article/actor\u0022\u003ECreative Choices\u003C/a\u003E. You can also get extra support from organisations like \u003Ca href=\u0022https://www.shapearts.org.uk/\u0022\u003EShape Arts\u003C/a\u003E, if you have a disability or special learning need.\u003C/p\u003E"
      },
      "HtbRegistrations": {
        "ContentItemIds": []
      }
    },
    "WhatItTakes": {
      "WhatItTakes": null,
      "WitDigitalSkillsLevel": {
        "Html": "\u003Cp\u003Eto be able to carry out basic tasks on a computer or hand-held device\u003C/p\u003E"
      },
      "WitRestrictions": {
        "ContentItemIds": []
      },
      "WitOtherRequirements": {
        "ContentItemIds": []
      }
    },
    "WhatYouWillDo": {
      "WhatYouWillDo": null,
      "DayToDayTasks": {
        "ContentItemIds": [
          "4h965agr6jvd4t16h78szdp0da",
          "47c3hy8c8jmnw6pj1gjktbx6cq",
          "413syxj9ypfj9xfqnas64j435r",
          "4829sqjmw5fjrr8zeaqmncgp57",
          "4xfw91zgm45kh2t00gvxcb9rck",
          "42ng8aprtrakgrnd3svrh894nf"
        ]
      },
      "WydWorkingEnvironment": {
        "ContentItemIds": [
          "49zvfh4ey09h8xadfn3fxg7kd0"
        ]
      },
      "WydWorkingLocation": {
        "ContentItemIds": [
          "4xen8teaq036mvapsany64f5nm"
        ]
      },
      "WydWorkingUniform": {
        "ContentItemIds": []
      }
    },
    "CareerPath": {
      "CareerPathAndProgression": {
        "Html": "\u003Cp\u003EIf you can show an agent you have potential they may put you forward for auditions and castings. Agents usually take a fee of about 10% to 25% from your earnings.\u003C/p\u003E\u003Cp\u003EYou could take further training and move into directing, scriptwriting, drama therapy or teaching.\u003C/p\u003E"
      },
      "ApprenticeshipStandards": {
        "ContentItemIds": []
      }
    },
    "GraphSyncPart": {
      "Text": "[js:configuration(\u0027ContentApiPrefix\u0027).toLowerCase() \u002B \u0027/jobprofile/8bc198bd-2c58-45f4-bb38-f95c353af680\u0027]"
    },
    "ContentItemId": "48g347xtegbhf7mfcg9wzsdhmw",
    "ContentItemVersionId": "40peaergnt8j6t5e0zz242r2nn",
    "ContentType": "JobProfile",
    "DisplayText": "Actor",
    "Latest": true,
    "Published": true,
    "ModifiedUtc": "2020-07-09T17:45:49.2613932Z",
    "PublishedUtc": "2020-07-09T17:45:49.2613932Z",
    "CreatedUtc": "2020-07-09T17:45:49.2613932Z",
    "Owner": "admin",
    "Author": "admin"
  }
      ]
    }
  ]
}